namespace/__init__.py
namespace/source/__init__.py
namespace/source/namespace.py
namespace/source/pretty_dict.py
namespace/tests/__init__.py
namespace/tests/fixtures.py
namespace/tests/test_namespace.py
namespace/tests/test_pretty_dict.py
j_namespace-2.1.0.dist-info/METADATA
j_namespace-2.1.0.dist-info/WHEEL
j_namespace-2.1.0.dist-info/top_level.txt
j_namespace-2.1.0.dist-info/RECORD
