Metadata-Version: 2.1
Name: j-namespace
Version: 2.1.0
Summary: Namespace
Home-page: https://github.com/Jakub21/Namespace
Author: Jakub21
License: MIT
